octo_pipeline_python/backends/docker/__init__.py
octo_pipeline_python/backends/docker/docker_backend.py
octo_pipeline_python/backends/docker/actions/__init__.py
octo_pipeline_python/backends/docker/actions/docker_build.py
octo_pipeline_python/backends/docker/models/__init__.py
octo_pipeline_python/backends/docker/models/docker_model.py
octo_pipeline_backend_docker_python-1.3.2.dist-info/LICENSE.txt
octo_pipeline_backend_docker_python-1.3.2.dist-info/METADATA
octo_pipeline_backend_docker_python-1.3.2.dist-info/README.md
octo_pipeline_backend_docker_python-1.3.2.dist-info/WHEEL
octo_pipeline_backend_docker_python-1.3.2.dist-info/top_level.txt
octo_pipeline_backend_docker_python-1.3.2.dist-info/RECORD
